FinPy-0.5.data/scripts/marketsim.py
FinPy-0.5.dist-info/DESCRIPTION.rst
FinPy-0.5.dist-info/METADATA
FinPy-0.5.dist-info/RECORD
FinPy-0.5.dist-info/WHEEL
FinPy-0.5.dist-info/metadata.json
FinPy-0.5.dist-info/top_level.txt
dyplot/__init__.py
dyplot/bar.py
dyplot/c3.py
dyplot/dygraphs.py
dyplot/hist.py
dyplot/nvd3.py
dyplot/pie.py
dyplot/scatter.py
finpy/__init__.py
finpy/data/DataPull.py
finpy/data/__init__.py
finpy/data/dataaccess.py
finpy/data/fetch.py
finpy/data/ofdp_datapull.py
finpy/financial/__init__.py
finpy/financial/equity.py
finpy/financial/fincommon.py
finpy/financial/order.py
finpy/financial/portfolio.py
finpy/financial/transaction.py
finpy/sim/__init__.py
finpy/sim/sim.py
finpy/utils/NYSE_dates.txt
finpy/utils/__init__.py
finpy/utils/eventprofiler.py
finpy/utils/fpdateutil.py
finpy/utils/utils.py
