Metadata-Version: 2.0
Name: FinPy
Version: 0.5
Summary: Financial Python. Using python to do stock analysis.
Home-page: http://pypi.python.org/pypi/FinPy/
Author: Tsung-Han Yang
Author-email: blacksburg98@yahoo.com
License: LICENSE.txt
Platform: UNKNOWN
Classifier: Intended Audience :: Financial and Insurance Industry
Classifier: Topic :: Office/Business :: Financial :: Investment
Classifier: Programming Language :: Python :: 3
Requires-Dist: NumPy (>=1.6.1)
Requires-Dist: dyplot (>=0.8.8)
Requires-Dist: pandas (>=0.7.3)
